napalm_opengear_ng/__init__.py
napalm_opengear_ng/opengear_ng.py
napalm_opengear_ng-0.1.5.dist-info/licenses/LICENSE
napalm_opengear_ng-0.1.5.dist-info/METADATA
napalm_opengear_ng-0.1.5.dist-info/WHEEL
napalm_opengear_ng-0.1.5.dist-info/top_level.txt
napalm_opengear_ng-0.1.5.dist-info/RECORD
