Metadata-Version: 2.4
Name: napalm-opengear-ng
Version: 0.1.5
Summary: NAPALM driver for Opengear CM81xx
Requires-Python: >=3.9
License-File: LICENSE
Requires-Dist: napalm>=4.1.0
Dynamic: license-file
